yt_dlp_plugins/extractor/webkit_jsi.py
yt_dlp_plugins/extractor/ytjsc.py
yt_dlp_plugins/webkit_jsi/README.md
yt_dlp_plugins/webkit_jsi/js_to_py.md
yt_dlp_plugins/webkit_jsi/examples/__init__.py
yt_dlp_plugins/webkit_jsi/examples/config.py
yt_dlp_plugins/webkit_jsi/examples/run.py
yt_dlp_plugins/webkit_jsi/examples/run_easy.py
yt_dlp_plugins/webkit_jsi/lib/.gitignore
yt_dlp_plugins/webkit_jsi/lib/__init__.py
yt_dlp_plugins/webkit_jsi/lib/api.py
yt_dlp_plugins/webkit_jsi/lib/consts.py
yt_dlp_plugins/webkit_jsi/lib/easy.py
yt_dlp_plugins/webkit_jsi/lib/logging.py
yt_dlp_plugins/webkit_jsi/lib/pyneapple_objc.py
yt_dlp_apple_webkit_jsi-0.0.8.dist-info/METADATA
yt_dlp_apple_webkit_jsi-0.0.8.dist-info/WHEEL
yt_dlp_apple_webkit_jsi-0.0.8.dist-info/licenses/LICENSE
yt_dlp_apple_webkit_jsi-0.0.8.dist-info/RECORD
