Metadata-Version: 2.4
Name: yt-dlp-apple-webkit-jsi
Version: 0.0.8
Maintainer: grqz
License-File: LICENSE
Keywords: yt-dlp,yt-dlp-jsc-provider,yt-dlp-plugin
Requires-Python: >=3.10
